[
  {
    "name": "London",
    "local_names": {
      "tl": "Londres",
      "li": "Londe",
      "ja": "ロンドン",
      "sa": "लन्डन्",
      "ko": "런던",
      "cy": "Llundain",
      "el": "Λονδίνο",
      "kl": "London",
      "an": "Londres",
      "bn": "লন্ডন",
      "bh": "लंदन",
      "de": "London",
      "id": "London",
      "yi": "לאנדאן",
      "hy": "Լոնդոն",
      "zu": "ILondon",
      "sd": "لنڊن",
      "kv": "Лондон",
      "tt": "Лондон",
      "ky": "Лондон",
      "mn": "Лондон",
      "ne": "लन्डन",
      "av": "Лондон",
      "ascii": "London",
      "es": "Londres",
      "pa": "ਲੰਡਨ",
      "ba": "Лондон",
      "sr": "Лондон",
      "lo": "ລອນດອນ",
      "ht": "Lonn",
      "tk": "London",
      "it": "Londra",
      "ps": "لندن",
      "om": "Landan",
      "sk": "Londýn",
      "sn": "London",
      "eo": "Londono",
      "mr": "लंडन",
      "ee": "London",
      "ff": "London",
      "ml": "ലണ്ടൻ",
      "zh": "伦敦",
      "ce": "Лондон",
      "uz": "London",
      "sh": "London",
      "sm": "Lonetona",
      "nn": "London",
      "or": "ଲଣ୍ଡନ",
      "fr": "Londres",
      "eu": "Londres",
      "fy": "Londen",
      "nv": "Tooh Dineʼé Bikin Haalʼá",
      "af": "Londen",
      "ms": "London",
      "te": "లండన్",
      "tw": "London",
      "feature_name": "London",
      "lv": "Londona",
      "sv": "London",
      "rm": "Londra",
      "no": "London",
      "sw": "London",
      "mg": "Lôndôna",
      "fa": "لندن",
      "gv": "Lunnin",
      "ny": "London",
      "hi": "लंदन",
      "ay": "London",
      "da": "London",
      "os": "Лондон",
      "cu": "Лондонъ",
      "fo": "London",
      "ru": "Лондон",
      "ha": "Landan",
      "bi": "London",
      "ku": "London",
      "gd": "Lunnainn",
      "sc": "Londra",
      "hr": "London",
      "mt": "Londra",
      "kn": "ಲಂಡನ್",
      "gn": "Lóndyre",
      "br": "Londrez",
      "na": "London",
      "io": "London",
      "my": "လန်ဒန်မြို့",
      "ka": "ლონდონი",
      "az": "London",
      "mk": "Лондон",
      "bg": "Лондон",
      "mi": "Rānana",
      "be": "Лондан",
      "et": "London",
      "kk": "Лондон",
      "kw": "Loundres",
      "co": "Londra",
      "bo": "ལོན་ཊོན།",
      "so": "London",
      "he": "לונדון",
      "tg": "Лондон",
      "sq": "Londra",
      "yo": "Lọndọnu",
      "uk": "Лондон",
      "is": "London",
      "nl": "Londen",
      "su": "London",
      "km": "ឡុងដ៍",
      "gu": "લંડન",
      "jv": "London",
      "gl": "Londres",
      "wa": "Londe",
      "ab": "Лондон",
      "am": "ለንደን",
      "fj": "Lodoni",
      "oc": "Londres",
      "ia": "London",
      "ca": "Londres",
      "ig": "London",
      "th": "ลอนดอน",
      "ur": "علاقہ لندن",
      "vo": "London",
      "ie": "London",
      "pl": "Londyn",
      "bm": "London",
      "vi": "Luân Đôn",
      "en": "London",
      "sl": "London",
      "bs": "London",
      "cv": "Лондон",
      "pt": "Londres",
      "st": "London",
      "ga": "Londain",
      "lt": "Londonas",
      "si": "ලන්ඩන්",
      "ug": "لوندۇن",
      "to": "Lonitoni",
      "ta": "இலண்டன்",
      "se": "London",
      "ln": "Lóndɛlɛ",
      "fi": "Lontoo",
      "tr": "Londra",
      "ar": "لندن",
      "ro": "Londra",
      "lb": "London",
      "cs": "Londýn",
      "wo": "Londar",
      "hu": "London",
      "qu": "London"
    },
    "lat": 51.5073219,
    "lon": -0.1276474,
    "country": "GB",
    "state": "England"
  }
]
